petram/__init__.py
petram/debug.py
petram/engine.py
petram/init_model.py
petram/mfem_config.py
petram/mfem_model.py
petram/mfem_viewer.py
petram/model.py
petram/namespace_mixin.py
petram/utils.py
petram/data/BilinearOps
petram/data/LinearOps
petram/data/icon/domain.png
petram/data/icon/dot.png
petram/data/icon/dot_bk.png
petram/data/icon/face.png
petram/data/icon/face_bk.png
petram/data/icon/form_BoundaryFlowIntegrator.png
petram/data/icon/form_BoundaryLFIntegrator.png
petram/data/icon/form_BoundaryMassIntegrator.png
petram/data/icon/form_BoundaryNormalLFIntegrator.png
petram/data/icon/form_BoundaryTangentialLFIntegrator.png
petram/data/icon/form_ConvectionIntegrator.png
petram/data/icon/form_CurlCurlIntegrator.png
petram/data/icon/form_DerivativeIntegrator1.png
petram/data/icon/form_DerivativeIntegrator2.png
petram/data/icon/form_DerivativeIntegrator3.png
petram/data/icon/form_DiffusionIntegrator.png
petram/data/icon/form_DivDivIntegrator.png
petram/data/icon/form_DomainLFIntegrator.png
petram/data/icon/form_ElasticityIntegrator.png
petram/data/icon/form_GroupConvectionIntegrator.png
petram/data/icon/form_MassIntegrator.png
petram/data/icon/form_MixedCrossCurlCurlIntegrator.png
petram/data/icon/form_MixedCrossCurlGradIntegrator.png
petram/data/icon/form_MixedCrossCurlIntegrator.png
petram/data/icon/form_MixedCrossGradCurlIntegrator.png
petram/data/icon/form_MixedCrossGradGradIntegrator.png
petram/data/icon/form_MixedCrossGradIntegrator.png
petram/data/icon/form_MixedCrossProductIntegrator.png
petram/data/icon/form_MixedCurlCurlIntegrator.png
petram/data/icon/form_MixedDirectionalDerivativeIntegrator.png
petram/data/icon/form_MixedDivGradIntegrator.png
petram/data/icon/form_MixedDotProductIntegrator.png
petram/data/icon/form_MixedGradDivIntegrator.png
petram/data/icon/form_MixedGradGradIntegrator.png
petram/data/icon/form_MixedScalarCrossCurlIntegrator.png
petram/data/icon/form_MixedScalarCrossGradIntegrator.png
PetraM_Base-2.1.40.dist-info/LICENSE
PetraM_Base-2.1.40.dist-info/METADATA
PetraM_Base-2.1.40.dist-info/WHEEL
PetraM_Base-2.1.40.dist-info/top_level.txt
PetraM_Base-2.1.40.dist-info/RECORD
