Metadata-Version: 2.1
Name: PetraM_Base
Version: 2.1.40
Summary: PetraM base package
Home-page: https://github.com/piScope/PetraM
Author: S. Shiraiwa
Author-email: shiraiwa@prenceton.edu
License: GNUv3
Keywords: MFEM physics
Classifier: Development Status :: 3 - Alpha
Classifier: Intended Audience :: Developers
Classifier: Topic :: Scientific/Engineering :: Physics
Classifier: License :: OSI Approved :: GNU General Public License v3 or later (GPLv3+)
Classifier: Programming Language :: Python :: 3.7
Classifier: Programming Language :: Python :: 3.8
Classifier: Programming Language :: Python :: 3.9
Classifier: Programming Language :: Python :: 3.10
Classifier: Programming Language :: Python :: 3.11
License-File: LICENSE
